cohort_creator/__init__.py
cohort_creator/_browse.py
cohort_creator/_cli.py
cohort_creator/_parsers.py
cohort_creator/_plotting.py
cohort_creator/_utils.py
cohort_creator/_version.py
cohort_creator/bagelify.py
cohort_creator/logger.py
cohort_creator/main.py
cohort_creator/data/__init__.py
cohort_creator/data/_update.py
cohort_creator/data/bids_filter.json
cohort_creator/data/columns_description.json
cohort_creator/data/config.yml
cohort_creator/data/non_openneuro.tsv
cohort_creator/data/openneuro.tsv
cohort_creator/data/read_nb_vols
cohort_creator/data/utils.py
cohort_creator-0.3.0.dist-info/METADATA
cohort_creator-0.3.0.dist-info/WHEEL
cohort_creator-0.3.0.dist-info/entry_points.txt
cohort_creator-0.3.0.dist-info/licenses/LICENSE
cohort_creator-0.3.0.dist-info/RECORD
