Metadata-Version: 2.3
Name: cohort_creator
Version: 0.3.0
Summary: Creates a neuroimaging cohort by aggregating data across datasets.
Project-URL: Bug trakcer, https://github.com/neurodatascience/cohort_creator/issues
Project-URL: Documentation, https://cohort-creator.readthedocs.io/en/latest/
Project-URL: Homepage, https://github.com/neurodatascience/cohort_creator
Author: Rémi Gau
Maintainer-email: Rémi Gau <remi.gau@gmail.com>
License: MIT
License-File: LICENSE
Classifier: Intended Audience :: Developers
Classifier: Intended Audience :: Science/Research
Classifier: License :: OSI Approved
Classifier: Operating System :: MacOS
Classifier: Operating System :: Microsoft :: Windows
Classifier: Operating System :: POSIX
Classifier: Operating System :: Unix
Classifier: Programming Language :: Python
Classifier: Programming Language :: Python :: 3.10
Classifier: Programming Language :: Python :: 3.11
Classifier: Programming Language :: Python :: 3.12
Classifier: Topic :: Scientific/Engineering
Classifier: Topic :: Software Development
Requires-Python: >=3.10
Requires-Dist: dash
Requires-Dist: dash-bootstrap-components
Requires-Dist: datalad
Requires-Dist: datalad-fuse
Requires-Dist: kaleido
Requires-Dist: matplotlib
Requires-Dist: mne
Requires-Dist: nibabel
Requires-Dist: pandas
Requires-Dist: plotly
Requires-Dist: pybids
Requires-Dist: pyyaml
Requires-Dist: requests
Requires-Dist: rich
Requires-Dist: rich-argparse
Provides-Extra: dev
Requires-Dist: cohort-creator[doc,test]; extra == 'dev'
Requires-Dist: gender-guesser; extra == 'dev'
Requires-Dist: pandas-stubs; extra == 'dev'
Requires-Dist: pre-commit; extra == 'dev'
Provides-Extra: doc
Requires-Dist: furo; extra == 'doc'
Requires-Dist: myst-parser; extra == 'doc'
Requires-Dist: numpydoc; extra == 'doc'
Requires-Dist: sphinx; extra == 'doc'
Requires-Dist: sphinx-argparse; extra == 'doc'
Requires-Dist: sphinx-copybutton; extra == 'doc'
Provides-Extra: docs
Requires-Dist: cohort-creator[doc]; extra == 'docs'
Provides-Extra: test
Requires-Dist: pytest; extra == 'test'
Requires-Dist: pytest-cov; extra == 'test'
Provides-Extra: tests
Requires-Dist: cohort-creator[test]; extra == 'tests'
